main.py
scoundrel-0.1.1.dist-info/licenses/LICENSE
scoundrel-0.1.1.dist-info/METADATA
scoundrel-0.1.1.dist-info/WHEEL
scoundrel-0.1.1.dist-info/entry_points.txt
scoundrel-0.1.1.dist-info/top_level.txt
scoundrel-0.1.1.dist-info/RECORD
