Metadata-Version: 2.4
Name: scoundrel
Version: 0.1.1
Summary: A Python implementation of the Scoundrel card game
Author-email: Ethan Gutierrez <ethanlizzard1123@gmail.com>
Maintainer-email: Ethan Gutierrez <ethanlizzard1123@gmail.com>
License-Expression: MIT
Project-URL: Homepage, https://github.com/Lizzard1123/scoundrel
Project-URL: Repository, https://github.com/Lizzard1123/scoundrel
Project-URL: Bug Reports, https://github.com/Lizzard1123/scoundrel/issues
Project-URL: Documentation, https://github.com/Lizzard1123/scoundrel#readme
Keywords: card-game,scoundrel,terminal,game,reinforcement-learning,mcts
Classifier: Development Status :: 3 - Alpha
Classifier: Intended Audience :: Developers
Classifier: Intended Audience :: End Users/Desktop
Classifier: Operating System :: OS Independent
Classifier: Programming Language :: Python :: 3
Classifier: Programming Language :: Python :: 3.10
Classifier: Programming Language :: Python :: 3.11
Classifier: Programming Language :: Python :: 3.12
Classifier: Topic :: Games/Entertainment :: Board Games
Classifier: Topic :: Scientific/Engineering :: Artificial Intelligence
Requires-Python: >=3.10
License-File: LICENSE
Requires-Dist: rich>=13.0.0
Dynamic: license-file
